pymatchers/__CreateRe.py
pymatchers/__Detector.py
pymatchers/__Html2Json.py
pymatchers/__init__.py
pymatchers/__NlpParser.py
pymatchers/__RegularCheck.py
pymatchers/__RegularParser.py
pymatchers/__Tag.py
pymatchers-0.1.0.dist-info/DESCRIPTION.rst
pymatchers-0.1.0.dist-info/LICENSE.txt
pymatchers-0.1.0.dist-info/METADATA
pymatchers-0.1.0.dist-info/metadata.json
pymatchers-0.1.0.dist-info/RECORD
pymatchers-0.1.0.dist-info/top_level.txt
pymatchers-0.1.0.dist-info/WHEEL
