Metadata-Version: 2.0
Name: pymatchers
Version: 0.1.0
Summary: Create the Best Universal Resolution Artifact
Home-page: https://github.com/SimonWang00/pymatchers
Author: simon Wang
Author-email: simon_wang00@163.com
License: MIT
Platform: any
Classifier: Intended Audience :: Developers
Classifier: License :: OSI Approved :: BSD License
Classifier: Operating System :: OS Independent
Classifier: Topic :: Software Development :: Libraries
Requires-Python: >=3
Requires-Dist: jieba
Requires-Dist: bs4
Requires-Dist: python-stdnum
